qiclib/__init__.py
qiclib/_version.py
qiclib/py.typed
qiclib/state_estimation.py
qiclib/code/__init__.py
qiclib/code/qi_command.py
qiclib/code/qi_dataflow.py
qiclib/code/qi_jobs.py
qiclib/code/qi_prog_builder.py
qiclib/code/qi_pulse.py
qiclib/code/qi_result.py
qiclib/code/qi_sample.py
qiclib/code/qi_seq_instructions.py
qiclib/code/qi_sequencer.py
qiclib/code/qi_simulate.py
qiclib/code/qi_types.py
qiclib/code/qi_util.py
qiclib/code/qi_var_definitions.py
qiclib/code/qi_visitor.py
qiclib/code/analysis/__init__.py
qiclib/code/analysis/qi_insert_mem_parameters.py
qiclib/coding/__init__.py
qiclib/coding/sequencercode.py
qiclib/experiment/SecondToneSweepR5.py
qiclib/experiment/__init__.py
qiclib/experiment/active_cooling_t1.py
qiclib/experiment/active_reset_t1.py
qiclib/experiment/base.py
qiclib/experiment/benchmarking.py
qiclib/experiment/collection.py
qiclib/experiment/correlation_calibration.py
qiclib/experiment/correlation_conv_all.py
qiclib/experiment/g1_correlation.py
qiclib/experiment/g1_correlation_conv.py
qiclib/experiment/g1_meas_setuptest.py
qiclib/experiment/g2_correlation.py
qiclib/experiment/g2_correlation_conv.py
qiclib/experiment/gx_correlation_base.py
qiclib/experiment/inverted_t1.py
qiclib/experiment/iq_clouds_multi_qfb.py
qiclib/experiment/iq_clouds_qfb_decay.py
qiclib/experiment/iq_clouds_ramsey.py
qiclib/experiment/iq_clouds_ringup.py
qiclib/experiment/multi_pi_t1.py
qiclib/experiment/qkit_virtual_awg.py
qiclib/experiment/quantum_jumps_long.py
qiclib/experiment/rabi_R5PG.py
qiclib/experiment/rabi_drag.py
qiclib/experiment/rabi_short.py
qiclib/experiment/readout_spectr.py
qiclib/experiment/resonator_ringup.py
qiclib/experiment/resonator_ringup_window.py
qiclib/experiment/stream_test.py
qiclib/experiment/qicode/__init__.py
qiclib/experiment/qicode/base.py
qiclib/experiment/qicode/collection.py
qiclib/experiment/qicode/data_handler.py
qiclib/experiment/qicode/data_provider.py
qiclib/experiment/qicode/fit_utils.py
qiclib/experiment/qicode/init_readout.py
qiclib-2.3.0.dist-info/METADATA
qiclib-2.3.0.dist-info/WHEEL
qiclib-2.3.0.dist-info/licenses/COPYING
qiclib-2.3.0.dist-info/RECORD
