Metadata-Version: 2.4
Name: qiclib
Version: 2.3.0
Summary: Library to connect to Quantum Interface's QiController.
Project-URL: Repository, https://github.com/quantuminterface/qiclib
Author-email: Quantum Interface <quantuminterface@ipe.kit.edu>
License:                     GNU GENERAL PUBLIC LICENSE
License-File: COPYING
Classifier: Development Status :: 3 - Alpha
Classifier: License :: OSI Approved :: GNU General Public License v3 or later (GPLv3+)
Classifier: Operating System :: OS Independent
Classifier: Programming Language :: Python :: 3
Classifier: Programming Language :: Python :: 3.10
Requires-Python: >=3.10
Requires-Dist: grpcio==1.73.1
Requires-Dist: ipywidgets>=8.1
Requires-Dist: lmfit>=1.3
Requires-Dist: matplotlib>=3.7
Requires-Dist: numpy>=1.24
Requires-Dist: protobuf==6.31.1
Requires-Dist: scipy>=1.10
Requires-Dist: tqdm>=4.67.1
Requires-Dist: wrapt>=1.16
Provides-Extra: qiskit
Requires-Dist: qiskit-aer>=0.15.1; extra == 'qiskit'
Requires-Dist: qiskit>=1.2.1; extra == 'qiskit'
Requires-Dist: tzlocal>=5.2; extra == 'qiskit'
